README
setup.cfg
setup.py
tuyaapi/__init__.py
tuyaapi.egg-info/PKG-INFO
tuyaapi.egg-info/SOURCES.txt
tuyaapi.egg-info/dependency_links.txt
tuyaapi.egg-info/requires.txt
tuyaapi.egg-info/top_level.txt